{
    "content": [
        {
            "latex_start": "\\int_{2}^{3} 2 x + x ^ {2} \\,dx",
            "start": "INT x:[2,3]. 2 * x + x ^ 2",
            "steps": [
                {
                    "latex_res": "\\frac{34}{3}",
                    "res": "34/3",
                    "rule": {
                        "name": "FullSimplify",
                        "str": "full simplify"
                    },
                    "type": "CalculationStep"
                }
            ],
            "type": "Calculation"
        },
        {
            "latex_start": "\\int_{0}^{1} (3 x + 1) ^ {-2} \\,dx",
            "start": "INT x:[0,1]. (3 * x + 1) ^ -2",
            "steps": [
                {
                    "latex_res": "\\int_{1}^{4} \\frac{1}{3} u ^ {-2} \\,du",
                    "res": "INT u:[1,4]. 1/3 * u ^ -2",
                    "rule": {
                        "latex_str": "substitute \\(u\\) for \\(3 x + 1\\)",
                        "name": "Substitution",
                        "str": "substitute u for 3 * x + 1",
                        "var_name": "u",
                        "var_subst": "3 * x + 1"
                    },
                    "type": "CalculationStep"
                },
                {
                    "latex_res": "\\frac{1}{4}",
                    "res": "1/4",
                    "rule": {
                        "name": "FullSimplify",
                        "str": "full simplify"
                    },
                    "type": "CalculationStep"
                }
            ],
            "type": "Calculation"
        },
        {
            "latex_start": "\\int_{0}^{1} e^{6 x} \\,dx",
            "start": "INT x:[0,1]. exp(6 * x)",
            "steps": [
                {
                    "latex_res": "\\int_{0}^{6} \\frac{1}{6} e^{u} \\,du",
                    "res": "INT u:[0,6]. 1/6 * exp(u)",
                    "rule": {
                        "latex_str": "substitute \\(u\\) for \\(6 x\\)",
                        "name": "Substitution",
                        "str": "substitute u for 6 * x",
                        "var_name": "u",
                        "var_subst": "6 * x"
                    },
                    "type": "CalculationStep"
                },
                {
                    "latex_res": "\\frac{1}{6} e^{6} - \\frac{1}{6}",
                    "res": "1/6 * exp(6) - 1/6",
                    "rule": {
                        "name": "FullSimplify",
                        "str": "full simplify"
                    },
                    "type": "CalculationStep"
                }
            ],
            "type": "Calculation"
        },
        {
            "latex_start": "\\int_{-1}^{2} x e^{x} \\,dx",
            "start": "INT x:[-1,2]. x * exp(x)",
            "steps": [
                {
                    "latex_res": "(\\left. x e^{x} \\right\\vert_{x=-1}^{2}) - (\\int_{-1}^{2} e^{x} \\,dx)",
                    "res": "([x * exp(x)]_x=-1,2) - (INT x:[-1,2]. exp(x))",
                    "rule": {
                        "latex_str": "integrate by parts \\(u \\to x, v \\to e^{x}\\)",
                        "name": "IntegrationByParts",
                        "str": "integrate by parts u -> x, v -> exp(x)",
                        "u": "x",
                        "v": "exp(x)"
                    },
                    "type": "CalculationStep"
                },
                {
                    "latex_res": "2 e^{-1} + e^{2}",
                    "res": "2 * exp(-1) + exp(2)",
                    "rule": {
                        "name": "FullSimplify",
                        "str": "full simplify"
                    },
                    "type": "CalculationStep"
                }
            ],
            "type": "Calculation"
        },
        {
            "latex_start": "\\int_{0}^{\\pi/4} \\sin{(x)} \\,dx",
            "start": "INT x:[0,pi / 4]. sin(x)",
            "steps": [
                {
                    "latex_res": "-\\frac{1}{2} \\sqrt{2} + 1",
                    "res": "-1/2 * sqrt(2) + 1",
                    "rule": {
                        "name": "FullSimplify",
                        "str": "full simplify"
                    },
                    "type": "CalculationStep"
                }
            ],
            "type": "Calculation"
        },
        {
            "latex_start": "\\int_{0}^{1} 3 x ^ {2} - x + 1 \\,dx",
            "start": "INT x:[0,1]. 3 * x ^ 2 - x + 1",
            "steps": [
                {
                    "latex_res": "\\frac{3}{2}",
                    "res": "3/2",
                    "rule": {
                        "name": "FullSimplify",
                        "str": "full simplify"
                    },
                    "type": "CalculationStep"
                }
            ],
            "type": "Calculation"
        },
        {
            "latex_start": "\\int_{1}^{2} x ^ {2} + \\frac{1}{x ^ {4}} \\,dx",
            "start": "INT x:[1,2]. x ^ 2 + 1 / x ^ 4",
            "steps": [
                {
                    "latex_res": "\\frac{21}{8}",
                    "res": "21/8",
                    "rule": {
                        "name": "FullSimplify",
                        "str": "full simplify"
                    },
                    "type": "CalculationStep"
                }
            ],
            "type": "Calculation"
        },
        {
            "latex_start": "\\int_{\\pi/3}^{\\pi} \\sin{(2 x + \\frac{\\pi}{3})} \\,dx",
            "start": "INT x:[pi / 3,pi]. sin(2 * x + pi / 3)",
            "steps": [
                {
                    "latex_res": "\\int_{\\pi}^{7/3 \\pi} \\frac{1}{2} \\sin{(u)} \\,du",
                    "res": "INT u:[pi,7/3 * pi]. 1/2 * sin(u)",
                    "rule": {
                        "latex_str": "substitute \\(u\\) for \\(2 x + \\frac{\\pi}{3}\\)",
                        "name": "Substitution",
                        "str": "substitute u for 2 * x + pi / 3",
                        "var_name": "u",
                        "var_subst": "2 * x + pi / 3"
                    },
                    "type": "CalculationStep"
                },
                {
                    "latex_res": "-\\frac{3}{4}",
                    "res": "-3/4",
                    "rule": {
                        "name": "FullSimplify",
                        "str": "full simplify"
                    },
                    "type": "CalculationStep"
                }
            ],
            "type": "Calculation"
        },
        {
            "latex_start": "\\int_{4}^{9} \\sqrt[3]{x} (\\sqrt{x} + 1) \\,dx",
            "start": "INT x:[4,9]. x ^ (1/3) * (x ^ (1/2) + 1)",
            "steps": [
                {
                    "latex_res": "\\int_{4}^{9} \\sqrt[3]{x} + x ^ {5/6} \\,dx",
                    "res": "INT x:[4,9]. x ^ (1/3) + x ^ (5/6)",
                    "rule": {
                        "name": "ExpandPolynomial",
                        "str": "expand polynomial"
                    },
                    "type": "CalculationStep"
                },
                {
                    "latex_res": "-\\frac{81}{11} 2 ^ {2/3} + \\frac{945}{44} 3 ^ {2/3}",
                    "res": "-81/11 * 2 ^ (2/3) + 945/44 * 3 ^ (2/3)",
                    "rule": {
                        "name": "FullSimplify",
                        "str": "full simplify"
                    },
                    "type": "CalculationStep"
                }
            ],
            "type": "Calculation"
        },
        {
            "latex_start": "\\int_{-1}^{0} \\frac{3 x ^ {4} + 3 x ^ {2} + 1}{x ^ {2} + 1} \\,dx",
            "start": "INT x:[-1,0]. (3 * x ^ 4 + 3 * x ^ 2 + 1) / (x ^ 2 + 1)",
            "steps": [
                {
                    "latex_res": "\\int_{-1}^{0} 3 x ^ {2} + \\frac{1}{x ^ {2} + 1} \\,dx",
                    "res": "INT x:[-1,0]. 3 * x ^ 2 + 1 / (x ^ 2 + 1)",
                    "rule": {
                        "name": "PolynomialDivision",
                        "str": "polynomial division"
                    },
                    "type": "CalculationStep"
                },
                {
                    "latex_res": "\\frac{1}{4} \\pi + 1",
                    "res": "1/4 * pi + 1",
                    "rule": {
                        "name": "FullSimplify",
                        "str": "full simplify"
                    },
                    "type": "CalculationStep"
                }
            ],
            "type": "Calculation"
        },
        {
            "latex_start": "\\int_{4}^{e + 3} \\frac{x ^ {3} - 12 x ^ {2} - 42}{x - 3} \\,dx",
            "start": "INT x:[4,exp(1) + 3]. (x ^ 3 - 12 * x ^ 2 - 42) / (x - 3)",
            "steps": [
                {
                    "latex_res": "\\int_{4}^{e + 3} x ^ {2} - 9 x - 27 - \\frac{123}{x - 3} \\,dx",
                    "res": "INT x:[4,exp(1) + 3]. x ^ 2 - 9 * x - 27 - 123 / (x - 3)",
                    "rule": {
                        "name": "PolynomialDivision",
                        "str": "polynomial division"
                    },
                    "type": "CalculationStep"
                },
                {
                    "latex_res": "-45 e - \\frac{3}{2} e^{2} + \\frac{1}{3} e^{3} + \\frac{277}{6} - 123 (\\int_{4}^{e + 3} (x - 3) ^ {-1} \\,dx)",
                    "res": "-45 * exp(1) - 3/2 * exp(2) + 1/3 * exp(3) + 277/6 - 123 * (INT x:[4,exp(1) + 3]. (x - 3) ^ -1)",
                    "rule": {
                        "name": "FullSimplify",
                        "str": "full simplify"
                    },
                    "type": "CalculationStep"
                },
                {
                    "latex_res": "-45 e - \\frac{3}{2} e^{2} + \\frac{1}{3} e^{3} + \\frac{277}{6} - 123 (\\int_{1}^{e} u ^ {-1} \\,du)",
                    "res": "-45 * exp(1) - 3/2 * exp(2) + 1/3 * exp(3) + 277/6 - 123 * (INT u:[1,exp(1)]. u ^ -1)",
                    "rule": {
                        "latex_str": "substitute \\(u\\) for \\(x - 3\\)",
                        "name": "Substitution",
                        "str": "substitute u for x - 3",
                        "var_name": "u",
                        "var_subst": "x - 3"
                    },
                    "type": "CalculationStep"
                },
                {
                    "latex_res": "-45 e - \\frac{3}{2} e^{2} + \\frac{1}{3} e^{3} - \\frac{461}{6}",
                    "res": "-45 * exp(1) - 3/2 * exp(2) + 1/3 * exp(3) - 461/6",
                    "rule": {
                        "name": "FullSimplify",
                        "str": "full simplify"
                    },
                    "type": "CalculationStep"
                }
            ],
            "type": "Calculation"
        },
        {
            "latex_start": "\\int_{0}^{\\pi/2} \\sin{(x)} \\cos^{3}(x) \\,dx",
            "start": "INT x:[0,pi / 2]. sin(x) * cos(x) ^ 3",
            "steps": [
                {
                    "latex_res": "\\int_{0}^{1} u ^ {3} \\,du",
                    "res": "INT u:[0,1]. u ^ 3",
                    "rule": {
                        "latex_str": "substitute \\(u\\) for \\(\\cos{(x)}\\)",
                        "name": "Substitution",
                        "str": "substitute u for cos(x)",
                        "var_name": "u",
                        "var_subst": "cos(x)"
                    },
                    "type": "CalculationStep"
                },
                {
                    "latex_res": "\\frac{1}{4}",
                    "res": "1/4",
                    "rule": {
                        "name": "FullSimplify",
                        "str": "full simplify"
                    },
                    "type": "CalculationStep"
                }
            ],
            "type": "Calculation"
        },
        {
            "latex_start": "\\int_{0}^{\\pi} 1 - \\sin^{3}(x) \\,dx",
            "start": "INT x:[0,pi]. 1 - sin(x) ^ 3",
            "steps": [
                {
                    "latex_res": "-(\\int_{0}^{\\pi} \\sin^{3}(x) \\,dx) + \\pi",
                    "res": "-(INT x:[0,pi]. sin(x) ^ 3) + pi",
                    "rule": {
                        "name": "FullSimplify",
                        "str": "full simplify"
                    },
                    "type": "CalculationStep"
                },
                {
                    "latex_res": "-(\\int_{0}^{\\pi} \\sin{(x)} \\sin^{2}(x) \\,dx) + \\pi",
                    "res": "-(INT x:[0,pi]. sin(x) * sin(x) ^ 2) + pi",
                    "rule": {
                        "loc": "0.0.0",
                        "name": "Equation",
                        "new_expr": "sin(x) * sin(x) ^ 2",
                        "str": "rewriting at 0.0.0"
                    },
                    "type": "CalculationStep"
                },
                {
                    "latex_res": "-(\\int_{0}^{\\pi} \\sin{(x)} (1 - \\cos^{2}(x)) \\,dx) + \\pi",
                    "res": "-(INT x:[0,pi]. sin(x) * (1 - cos(x) ^ 2)) + pi",
                    "rule": {
                        "loc": "0.0.0.1",
                        "name": "RewriteTrigonometric",
                        "rule_name": "TR5",
                        "str": "rewrite trigonometric at 0.0.0.1"
                    },
                    "type": "CalculationStep"
                },
                {
                    "latex_res": "-(\\int_{-1}^{1} -u ^ {2} + 1 \\,du) + \\pi",
                    "res": "-(INT u:[-1,1]. -(u ^ 2) + 1) + pi",
                    "rule": {
                        "latex_str": "substitute \\(u\\) for \\(\\cos{(x)}\\)",
                        "name": "Substitution",
                        "str": "substitute u for cos(x)",
                        "var_name": "u",
                        "var_subst": "cos(x)"
                    },
                    "type": "CalculationStep"
                },
                {
                    "latex_res": "\\pi - \\frac{4}{3}",
                    "res": "pi - 4/3",
                    "rule": {
                        "name": "FullSimplify",
                        "str": "full simplify"
                    },
                    "type": "CalculationStep"
                }
            ],
            "type": "Calculation"
        },
        {
            "latex_start": "\\int_{\\pi/6}^{\\pi/2} \\cos^{2}(x) \\,dx",
            "start": "INT x:[pi / 6,pi / 2]. cos(x) ^ 2",
            "steps": [
                {
                    "latex_res": "\\int_{\\pi/6}^{\\pi/2} \\frac{\\cos{(2 x)}}{2} + \\frac{1}{2} \\,dx",
                    "res": "INT x:[pi / 6,pi / 2]. cos(2 * x) / 2 + 1/2",
                    "rule": {
                        "loc": "0",
                        "name": "RewriteTrigonometric",
                        "rule_name": "TR7",
                        "str": "rewrite trigonometric at 0"
                    },
                    "type": "CalculationStep"
                },
                {
                    "latex_res": "\\frac{1}{2} (\\int_{1/6 \\pi}^{1/2 \\pi} \\cos{(2 x)} \\,dx) + \\frac{1}{6} \\pi",
                    "res": "1/2 * (INT x:[1/6 * pi,1/2 * pi]. cos(2 * x)) + 1/6 * pi",
                    "rule": {
                        "name": "FullSimplify",
                        "str": "full simplify"
                    },
                    "type": "CalculationStep"
                },
                {
                    "latex_res": "\\frac{1}{2} (\\int_{1/3 \\pi}^{\\pi} \\frac{1}{2} \\cos{(u)} \\,du) + \\frac{1}{6} \\pi",
                    "res": "1/2 * (INT u:[1/3 * pi,pi]. 1/2 * cos(u)) + 1/6 * pi",
                    "rule": {
                        "latex_str": "substitute \\(u\\) for \\(2 x\\)",
                        "name": "Substitution",
                        "str": "substitute u for 2 * x",
                        "var_name": "u",
                        "var_subst": "2 * x"
                    },
                    "type": "CalculationStep"
                },
                {
                    "latex_res": "-\\frac{1}{8} \\sqrt{3} + \\frac{1}{6} \\pi",
                    "res": "-1/8 * sqrt(3) + 1/6 * pi",
                    "rule": {
                        "name": "FullSimplify",
                        "str": "full simplify"
                    },
                    "type": "CalculationStep"
                }
            ],
            "type": "Calculation"
        },
        {
            "latex_start": "\\int_{0}^{1} \\sqrt{1 - x ^ {2}} \\,dx",
            "start": "INT x:[0,1]. (1 - x ^ 2) ^ (1/2)",
            "steps": [
                {
                    "latex_res": "\\int_{0}^{\\pi/2} \\sqrt{1 - \\sin^{2}(u)} \\cos{(u)} \\,du",
                    "res": "INT u:[0,pi / 2]. (1 - sin(u) ^ 2) ^ (1/2) * cos(u)",
                    "rule": {
                        "latex_str": "inverse substitution for \\(\\sin{(u)}\\)",
                        "name": "SubstitutionInverse",
                        "str": "inverse substitution for sin(u)",
                        "var_name": "u",
                        "var_subst": "sin(u)"
                    },
                    "type": "CalculationStep"
                },
                {
                    "latex_res": "\\int_{0}^{\\pi/2} \\sqrt{\\cos^{2}(u)} \\cos{(u)} \\,du",
                    "res": "INT u:[0,pi / 2]. cos(u) ^ 2 ^ (1/2) * cos(u)",
                    "rule": {
                        "loc": "0.0.0",
                        "name": "RewriteTrigonometric",
                        "rule_name": "TR5",
                        "str": "rewrite trigonometric at 0.0.0"
                    },
                    "type": "CalculationStep"
                },
                {
                    "latex_res": "\\int_{0}^{1/2 \\pi} \\cos{(u)} \\left| \\cos{(u)} \\right| \\,du",
                    "res": "INT u:[0,1/2 * pi]. cos(u) * abs(cos(u))",
                    "rule": {
                        "name": "FullSimplify",
                        "str": "full simplify"
                    },
                    "type": "CalculationStep"
                },
                {
                    "latex_res": "\\int_{0}^{\\pi/2} \\cos{(u)} \\cos{(u)} \\,du",
                    "res": "INT u:[0,pi / 2]. cos(u) * cos(u)",
                    "rule": {
                        "name": "ElimAbs",
                        "str": "eliminate absolute values"
                    },
                    "type": "CalculationStep"
                },
                {
                    "latex_res": "\\int_{0}^{1/2 \\pi} \\cos^{2}(u) \\,du",
                    "res": "INT u:[0,1/2 * pi]. cos(u) ^ 2",
                    "rule": {
                        "name": "FullSimplify",
                        "str": "full simplify"
                    },
                    "type": "CalculationStep"
                },
                {
                    "latex_res": "\\int_{0}^{1/2 \\pi} \\frac{\\cos{(2 u)}}{2} + \\frac{1}{2} \\,du",
                    "res": "INT u:[0,1/2 * pi]. cos(2 * u) / 2 + 1/2",
                    "rule": {
                        "loc": "0",
                        "name": "RewriteTrigonometric",
                        "rule_name": "TR7",
                        "str": "rewrite trigonometric at 0"
                    },
                    "type": "CalculationStep"
                },
                {
                    "latex_res": "\\int_{0}^{\\pi} \\frac{1}{4} \\cos{(v)} + \\frac{1}{4} \\,dv",
                    "res": "INT v:[0,pi]. 1/4 * cos(v) + 1/4",
                    "rule": {
                        "latex_str": "substitute \\(v\\) for \\(2 u\\)",
                        "name": "Substitution",
                        "str": "substitute v for 2 * u",
                        "var_name": "v",
                        "var_subst": "2 * u"
                    },
                    "type": "CalculationStep"
                },
                {
                    "latex_res": "\\frac{1}{4} \\pi",
                    "res": "1/4 * pi",
                    "rule": {
                        "name": "FullSimplify",
                        "str": "full simplify"
                    },
                    "type": "CalculationStep"
                }
            ],
            "type": "Calculation"
        },
        {
            "latex_start": "\\int_{0}^{\\sqrt{2}} \\sqrt{2 - x ^ {2}} \\,dx",
            "start": "INT x:[0,sqrt(2)]. sqrt(2 - x ^ 2)",
            "steps": [
                {
                    "latex_res": "\\int_{0}^{\\pi/2} \\sqrt{2 - (\\sqrt{2} \\sin{(u)}) ^ {2}} (\\sqrt{2} \\cos{(u)}) \\,du",
                    "res": "INT u:[0,pi / 2]. sqrt(2 - (sqrt(2) * sin(u)) ^ 2) * (sqrt(2) * cos(u))",
                    "rule": {
                        "latex_str": "inverse substitution for \\(\\sqrt{2} \\sin{(u)}\\)",
                        "name": "SubstitutionInverse",
                        "str": "inverse substitution for sqrt(2) * sin(u)",
                        "var_name": "u",
                        "var_subst": "sqrt(2) * sin(u)"
                    },
                    "type": "CalculationStep"
                },
                {
                    "latex_res": "\\sqrt{2} (\\int_{0}^{1/2 \\pi} \\cos{(u)} \\sqrt{-2 \\sin^{2}(u) + 2} \\,du)",
                    "res": "sqrt(2) * (INT u:[0,1/2 * pi]. cos(u) * sqrt(-2 * sin(u) ^ 2 + 2))",
                    "rule": {
                        "name": "FullSimplify",
                        "str": "full simplify"
                    },
                    "type": "CalculationStep"
                },
                {
                    "latex_res": "\\sqrt{2} (\\int_{0}^{1/2 \\pi} \\cos{(u)} \\sqrt{2 \\cos^{2}(u)} \\,du)",
                    "res": "sqrt(2) * (INT u:[0,1/2 * pi]. cos(u) * sqrt(2 * cos(u) ^ 2))",
                    "rule": {
                        "loc": "1.0.1.0",
                        "name": "RewriteTrigonometric",
                        "rule_name": "TR5",
                        "str": "rewrite trigonometric at 1.0.1.0"
                    },
                    "type": "CalculationStep"
                },
                {
                    "latex_res": "2 (\\int_{0}^{1/2 \\pi} \\cos{(u)} \\left| \\cos{(u)} \\right| \\,du)",
                    "res": "2 * (INT u:[0,1/2 * pi]. cos(u) * abs(cos(u)))",
                    "rule": {
                        "name": "FullSimplify",
                        "str": "full simplify"
                    },
                    "type": "CalculationStep"
                },
                {
                    "latex_res": "2 (\\int_{0}^{\\pi/2} \\cos{(u)} \\cos{(u)} \\,du)",
                    "res": "2 * (INT u:[0,pi / 2]. cos(u) * cos(u))",
                    "rule": {
                        "loc": "1",
                        "name": "ElimAbs",
                        "str": "eliminate absolute values at 1"
                    },
                    "type": "CalculationStep"
                },
                {
                    "latex_res": "2 (\\int_{0}^{1/2 \\pi} \\cos^{2}(u) \\,du)",
                    "res": "2 * (INT u:[0,1/2 * pi]. cos(u) ^ 2)",
                    "rule": {
                        "name": "FullSimplify",
                        "str": "full simplify"
                    },
                    "type": "CalculationStep"
                },
                {
                    "latex_res": "2 (\\int_{0}^{1/2 \\pi} \\frac{\\cos{(2 u)}}{2} + \\frac{1}{2} \\,du)",
                    "res": "2 * (INT u:[0,1/2 * pi]. cos(2 * u) / 2 + 1/2)",
                    "rule": {
                        "loc": "1.0",
                        "name": "RewriteTrigonometric",
                        "rule_name": "TR7",
                        "str": "rewrite trigonometric at 1.0"
                    },
                    "type": "CalculationStep"
                },
                {
                    "latex_res": "2 (\\int_{0}^{\\pi} \\frac{1}{4} \\cos{(v)} + \\frac{1}{4} \\,dv)",
                    "res": "2 * (INT v:[0,pi]. 1/4 * cos(v) + 1/4)",
                    "rule": {
                        "latex_str": "substitute \\(v\\) for \\(2 u\\)",
                        "name": "Substitution",
                        "str": "substitute v for 2 * u",
                        "var_name": "v",
                        "var_subst": "2 * u"
                    },
                    "type": "CalculationStep"
                },
                {
                    "latex_res": "\\frac{1}{2} \\pi",
                    "res": "1/2 * pi",
                    "rule": {
                        "name": "FullSimplify",
                        "str": "full simplify"
                    },
                    "type": "CalculationStep"
                }
            ],
            "type": "Calculation"
        },
        {
            "latex_start": "\\int_{-\\sqrt{2}}^{\\sqrt{2}} \\sqrt{8 - 2 y ^ {2}} \\,dy",
            "start": "INT y:[-sqrt(2),sqrt(2)]. sqrt(8 - 2 * y ^ 2)",
            "steps": [
                {
                    "latex_res": "\\int_{-\\pi/4}^{\\pi/4} \\sqrt{8 - 2 (2 \\sin{(u)}) ^ {2}} (2 \\cos{(u)}) \\,du",
                    "res": "INT u:[-pi / 4,pi / 4]. sqrt(8 - 2 * (2 * sin(u)) ^ 2) * (2 * cos(u))",
                    "rule": {
                        "latex_str": "inverse substitution for \\(2 \\sin{(u)}\\)",
                        "name": "SubstitutionInverse",
                        "str": "inverse substitution for 2 * sin(u)",
                        "var_name": "u",
                        "var_subst": "2 * sin(u)"
                    },
                    "type": "CalculationStep"
                },
                {
                    "latex_res": "4 (\\int_{0}^{1/4 \\pi} \\cos{(u)} \\sqrt{-8 \\sin^{2}(u) + 8} \\,du)",
                    "res": "4 * (INT u:[0,1/4 * pi]. cos(u) * sqrt(-8 * sin(u) ^ 2 + 8))",
                    "rule": {
                        "name": "FullSimplify",
                        "str": "full simplify"
                    },
                    "type": "CalculationStep"
                },
                {
                    "latex_res": "4 (\\int_{0}^{1/4 \\pi} \\cos{(u)} \\sqrt{8 \\cos^{2}(u)} \\,du)",
                    "res": "4 * (INT u:[0,1/4 * pi]. cos(u) * sqrt(8 * cos(u) ^ 2))",
                    "rule": {
                        "loc": "1.0.1.0",
                        "name": "RewriteTrigonometric",
                        "rule_name": "TR5",
                        "str": "rewrite trigonometric at 1.0.1.0"
                    },
                    "type": "CalculationStep"
                },
                {
                    "latex_res": "8 \\sqrt{2} (\\int_{0}^{1/4 \\pi} \\cos{(u)} \\left| \\cos{(u)} \\right| \\,du)",
                    "res": "8 * sqrt(2) * (INT u:[0,1/4 * pi]. cos(u) * abs(cos(u)))",
                    "rule": {
                        "name": "FullSimplify",
                        "str": "full simplify"
                    },
                    "type": "CalculationStep"
                },
                {
                    "latex_res": "8 \\sqrt{2} (\\int_{0}^{\\pi/4} \\cos{(u)} \\cos{(u)} \\,du)",
                    "res": "8 * sqrt(2) * (INT u:[0,pi / 4]. cos(u) * cos(u))",
                    "rule": {
                        "loc": "1",
                        "name": "ElimAbs",
                        "str": "eliminate absolute values at 1"
                    },
                    "type": "CalculationStep"
                },
                {
                    "latex_res": "8 \\sqrt{2} (\\int_{0}^{1/4 \\pi} \\cos^{2}(u) \\,du)",
                    "res": "8 * sqrt(2) * (INT u:[0,1/4 * pi]. cos(u) ^ 2)",
                    "rule": {
                        "name": "FullSimplify",
                        "str": "full simplify"
                    },
                    "type": "CalculationStep"
                },
                {
                    "latex_res": "8 \\sqrt{2} (\\int_{0}^{1/4 \\pi} \\frac{\\cos{(2 u)}}{2} + \\frac{1}{2} \\,du)",
                    "res": "8 * sqrt(2) * (INT u:[0,1/4 * pi]. cos(2 * u) / 2 + 1/2)",
                    "rule": {
                        "loc": "1.0",
                        "name": "RewriteTrigonometric",
                        "rule_name": "TR7",
                        "str": "rewrite trigonometric at 1.0"
                    },
                    "type": "CalculationStep"
                },
                {
                    "latex_res": "8 \\sqrt{2} (\\int_{0}^{1/2 \\pi} \\frac{1}{4} \\cos{(v)} + \\frac{1}{4} \\,dv)",
                    "res": "8 * sqrt(2) * (INT v:[0,1/2 * pi]. 1/4 * cos(v) + 1/4)",
                    "rule": {
                        "latex_str": "substitute \\(v\\) for \\(2 u\\)",
                        "name": "Substitution",
                        "str": "substitute v for 2 * u",
                        "var_name": "v",
                        "var_subst": "2 * u"
                    },
                    "type": "CalculationStep"
                },
                {
                    "latex_res": "\\sqrt{2} \\pi + 2 \\sqrt{2}",
                    "res": "sqrt(2) * pi + 2 * sqrt(2)",
                    "rule": {
                        "name": "FullSimplify",
                        "str": "full simplify"
                    },
                    "type": "CalculationStep"
                }
            ],
            "type": "Calculation"
        },
        {
            "latex_start": "\\int_{1/\\sqrt{2}}^{1} \\frac{\\sqrt{1 - x ^ {2}}}{x ^ {2}} \\,dx",
            "start": "INT x:[1 / sqrt(2),1]. sqrt(1 - x ^ 2) / x ^ 2",
            "steps": [
                {
                    "latex_res": "\\int_{\\pi/4}^{\\pi/2} \\frac{\\sqrt{1 - \\sin^{2}(u)}}{\\sin^{2}(u)} \\cos{(u)} \\,du",
                    "res": "INT u:[pi / 4,pi / 2]. sqrt(1 - sin(u) ^ 2) / sin(u) ^ 2 * cos(u)",
                    "rule": {
                        "latex_str": "inverse substitution for \\(\\sin{(u)}\\)",
                        "name": "SubstitutionInverse",
                        "str": "inverse substitution for sin(u)",
                        "var_name": "u",
                        "var_subst": "sin(u)"
                    },
                    "type": "CalculationStep"
                },
                {
                    "latex_res": "\\int_{1/4 \\pi}^{1/2 \\pi} \\cos{(u)} \\sin^{-2}(u) \\sqrt{-\\sin^{2}(u) + 1} \\,du",
                    "res": "INT u:[1/4 * pi,1/2 * pi]. cos(u) * sin(u) ^ -2 * sqrt(-(sin(u) ^ 2) + 1)",
                    "rule": {
                        "name": "FullSimplify",
                        "str": "full simplify"
                    },
                    "type": "CalculationStep"
                },
                {
                    "latex_res": "\\int_{1/4 \\pi}^{1/2 \\pi} \\cos{(u)} \\sin^{-2}(u) \\sqrt{\\cos^{2}(u)} \\,du",
                    "res": "INT u:[1/4 * pi,1/2 * pi]. cos(u) * sin(u) ^ -2 * sqrt(cos(u) ^ 2)",
                    "rule": {
                        "loc": "0.1.0",
                        "name": "RewriteTrigonometric",
                        "rule_name": "TR5",
                        "str": "rewrite trigonometric at 0.1.0"
                    },
                    "type": "CalculationStep"
                },
                {
                    "latex_res": "\\int_{1/4 \\pi}^{1/2 \\pi} \\cos{(u)} \\sin^{-2}(u) \\left| \\cos{(u)} \\right| \\,du",
                    "res": "INT u:[1/4 * pi,1/2 * pi]. cos(u) * sin(u) ^ -2 * abs(cos(u))",
                    "rule": {
                        "name": "FullSimplify",
                        "str": "full simplify"
                    },
                    "type": "CalculationStep"
                },
                {
                    "latex_res": "\\int_{\\pi/4}^{\\pi/2} \\cos{(u)} \\sin^{-2}(u) \\cos{(u)} \\,du",
                    "res": "INT u:[pi / 4,pi / 2]. cos(u) * sin(u) ^ -2 * cos(u)",
                    "rule": {
                        "name": "ElimAbs",
                        "str": "eliminate absolute values"
                    },
                    "type": "CalculationStep"
                },
                {
                    "latex_res": "\\int_{1/4 \\pi}^{1/2 \\pi} \\cos^{2}(u) \\sin^{-2}(u) \\,du",
                    "res": "INT u:[1/4 * pi,1/2 * pi]. cos(u) ^ 2 * sin(u) ^ -2",
                    "rule": {
                        "name": "FullSimplify",
                        "str": "full simplify"
                    },
                    "type": "CalculationStep"
                },
                {
                    "latex_res": "\\int_{1/4 \\pi}^{1/2 \\pi} (1 - \\sin^{2}(u)) \\sin^{-2}(u) \\,du",
                    "res": "INT u:[1/4 * pi,1/2 * pi]. (1 - sin(u) ^ 2) * sin(u) ^ -2",
                    "rule": {
                        "loc": "0.0",
                        "name": "RewriteTrigonometric",
                        "rule_name": "TR6",
                        "str": "rewrite trigonometric at 0.0"
                    },
                    "type": "CalculationStep"
                },
                {
                    "latex_res": "\\int_{1/4 \\pi}^{1/2 \\pi} \\sin^{-2}(u) - 1 \\,du",
                    "res": "INT u:[1/4 * pi,1/2 * pi]. sin(u) ^ -2 - 1",
                    "rule": {
                        "name": "ExpandPolynomial",
                        "str": "expand polynomial"
                    },
                    "type": "CalculationStep"
                },
                {
                    "latex_res": "(\\int_{1/4 \\pi}^{1/2 \\pi} \\sin^{-2}(u) \\,du) - \\frac{1}{4} \\pi",
                    "res": "(INT u:[1/4 * pi,1/2 * pi]. sin(u) ^ -2) - 1/4 * pi",
                    "rule": {
                        "name": "FullSimplify",
                        "str": "full simplify"
                    },
                    "type": "CalculationStep"
                },
                {
                    "latex_res": "(\\int_{1/4 \\pi}^{1/2 \\pi} \\csc^{2}(u) \\,du) - \\frac{1}{4} \\pi",
                    "res": "(INT u:[1/4 * pi,1/2 * pi]. csc(u) ^ 2) - 1/4 * pi",
                    "rule": {
                        "loc": "0.0",
                        "name": "RewriteTrigonometric",
                        "rule_name": "TR111",
                        "str": "rewrite trigonometric at 0.0"
                    },
                    "type": "CalculationStep"
                },
                {
                    "latex_res": "-\\frac{1}{4} \\pi + 1",
                    "res": "-1/4 * pi + 1",
                    "rule": {
                        "name": "FullSimplify",
                        "str": "full simplify"
                    },
                    "type": "CalculationStep"
                }
            ],
            "type": "Calculation"
        },
        {
            "latex_start": "\\int_{-1}^{1} \\frac{x}{\\sqrt{5 - 4 x}} \\,dx",
            "start": "INT x:[-1,1]. x / sqrt(5 - 4 * x)",
            "steps": [
                {
                    "latex_res": "\\int_{1}^{9} \\frac{1}{4} u ^ {-1/2} (-\\frac{1}{4} u + \\frac{5}{4}) \\,du",
                    "res": "INT u:[1,9]. 1/4 * u ^ (-1/2) * (-1/4 * u + 5/4)",
                    "rule": {
                        "latex_str": "substitute \\(u\\) for \\(5 - 4 x\\)",
                        "name": "Substitution",
                        "str": "substitute u for 5 - 4 * x",
                        "var_name": "u",
                        "var_subst": "5 - 4 * x"
                    },
                    "type": "CalculationStep"
                },
                {
                    "latex_res": "\\int_{1}^{9} \\frac{5}{16} u ^ {-1/2} - \\frac{1}{16} \\sqrt{u} \\,du",
                    "res": "INT u:[1,9]. 5/16 * u ^ (-1/2) - 1/16 * sqrt(u)",
                    "rule": {
                        "name": "ExpandPolynomial",
                        "str": "expand polynomial"
                    },
                    "type": "CalculationStep"
                },
                {
                    "latex_res": "\\frac{1}{6}",
                    "res": "1/6",
                    "rule": {
                        "name": "FullSimplify",
                        "str": "full simplify"
                    },
                    "type": "CalculationStep"
                }
            ],
            "type": "Calculation"
        },
        {
            "latex_start": "\\int_{1}^{4} \\frac{1}{1 + \\sqrt{x}} \\,dx",
            "start": "INT x:[1,4]. 1 / (1 + sqrt(x))",
            "steps": [
                {
                    "latex_res": "\\int_{1}^{2} 2 u (u + 1) ^ {-1} \\,du",
                    "res": "INT u:[1,2]. 2 * u * (u + 1) ^ -1",
                    "rule": {
                        "latex_str": "substitute \\(u\\) for \\(\\sqrt{x}\\)",
                        "name": "Substitution",
                        "str": "substitute u for sqrt(x)",
                        "var_name": "u",
                        "var_subst": "sqrt(x)"
                    },
                    "type": "CalculationStep"
                },
                {
                    "latex_res": "\\int_{2}^{3} v ^ {-1} (2 v - 2) \\,dv",
                    "res": "INT v:[2,3]. v ^ -1 * (2 * v - 2)",
                    "rule": {
                        "latex_str": "substitute \\(v\\) for \\(u + 1\\)",
                        "name": "Substitution",
                        "str": "substitute v for u + 1",
                        "var_name": "v",
                        "var_subst": "u + 1"
                    },
                    "type": "CalculationStep"
                },
                {
                    "latex_res": "\\int_{2}^{3} -2 v ^ {-1} + 2 \\,dv",
                    "res": "INT v:[2,3]. -2 * v ^ -1 + 2",
                    "rule": {
                        "name": "ExpandPolynomial",
                        "str": "expand polynomial"
                    },
                    "type": "CalculationStep"
                },
                {
                    "latex_res": "2 \\log{(2)} - 2 \\log{(3)} + 2",
                    "res": "2 * log(2) - 2 * log(3) + 2",
                    "rule": {
                        "name": "FullSimplify",
                        "str": "full simplify"
                    },
                    "type": "CalculationStep"
                }
            ],
            "type": "Calculation"
        },
        {
            "latex_start": "\\int_{3/4}^{1} \\frac{1}{\\sqrt{1 - x} - 1} \\,dx",
            "start": "INT x:[3/4,1]. 1 / (sqrt(1 - x) - 1)",
            "steps": [
                {
                    "latex_res": "\\int_{0}^{1/2} 2 u (u - 1) ^ {-1} \\,du",
                    "res": "INT u:[0,1/2]. 2 * u * (u - 1) ^ -1",
                    "rule": {
                        "latex_str": "substitute \\(u\\) for \\(\\sqrt{1 - x}\\)",
                        "name": "Substitution",
                        "str": "substitute u for sqrt(1 - x)",
                        "var_name": "u",
                        "var_subst": "sqrt(1 - x)"
                    },
                    "type": "CalculationStep"
                },
                {
                    "latex_res": "\\int_{-1}^{-1/2} v ^ {-1} (2 v + 2) \\,dv",
                    "res": "INT v:[-1,-1/2]. v ^ -1 * (2 * v + 2)",
                    "rule": {
                        "latex_str": "substitute \\(v\\) for \\(u - 1\\)",
                        "name": "Substitution",
                        "str": "substitute v for u - 1",
                        "var_name": "v",
                        "var_subst": "u - 1"
                    },
                    "type": "CalculationStep"
                },
                {
                    "latex_res": "\\int_{-1}^{-1/2} 2 v ^ {-1} + 2 \\,dv",
                    "res": "INT v:[-1,-1/2]. 2 * v ^ -1 + 2",
                    "rule": {
                        "name": "ExpandPolynomial",
                        "str": "expand polynomial"
                    },
                    "type": "CalculationStep"
                },
                {
                    "latex_res": "-2 \\log{(2)} + 1",
                    "res": "-2 * log(2) + 1",
                    "rule": {
                        "name": "FullSimplify",
                        "str": "full simplify"
                    },
                    "type": "CalculationStep"
                }
            ],
            "type": "Calculation"
        },
        {
            "latex_start": "\\int_{0}^{1} t e^{-t ^ {2}/2} \\,dt",
            "start": "INT t:[0,1]. t * exp(-(t ^ 2) / 2)",
            "steps": [
                {
                    "latex_res": "\\int_{-1/2}^{0} e^{u} \\,du",
                    "res": "INT u:[-1/2,0]. exp(u)",
                    "rule": {
                        "latex_str": "substitute \\(u\\) for \\(\\frac{-t ^ {2}}{2}\\)",
                        "name": "Substitution",
                        "str": "substitute u for -(t ^ 2) / 2",
                        "var_name": "u",
                        "var_subst": "-(t ^ 2) / 2"
                    },
                    "type": "CalculationStep"
                },
                {
                    "latex_res": "-e^{-1/2} + 1",
                    "res": "-exp(-1/2) + 1",
                    "rule": {
                        "name": "FullSimplify",
                        "str": "full simplify"
                    },
                    "type": "CalculationStep"
                }
            ],
            "type": "Calculation"
        },
        {
            "latex_start": "\\int_{1}^{e^{2}} \\frac{1}{x \\sqrt{1 + \\log{(x)}}} \\,dx",
            "start": "INT x:[1,exp(2)]. 1 / (x * sqrt(1 + log(x)))",
            "steps": [
                {
                    "latex_res": "\\int_{1}^{3} u ^ {-1/2} \\,du",
                    "res": "INT u:[1,3]. u ^ (-1/2)",
                    "rule": {
                        "latex_str": "substitute \\(u\\) for \\(1 + \\log{(x)}\\)",
                        "name": "Substitution",
                        "str": "substitute u for 1 + log(x)",
                        "var_name": "u",
                        "var_subst": "1 + log(x)"
                    },
                    "type": "CalculationStep"
                },
                {
                    "latex_res": "2 \\sqrt{3} - 2",
                    "res": "2 * sqrt(3) - 2",
                    "rule": {
                        "name": "FullSimplify",
                        "str": "full simplify"
                    },
                    "type": "CalculationStep"
                }
            ],
            "type": "Calculation"
        },
        {
            "latex_start": "\\int_{-2}^{0} \\frac{x + 2}{x ^ {2} + 2 x + 2} \\,dx",
            "start": "INT x:[-2,0]. (x + 2) / (x ^ 2 + 2 * x + 2)",
            "steps": [
                {
                    "latex_res": "\\int_{-2}^{0} \\frac{x + 2}{(x + 1) ^ {2} + 1} \\,dx",
                    "res": "INT x:[-2,0]. (x + 2) / ((x + 1) ^ 2 + 1)",
                    "rule": {
                        "loc": "0.1",
                        "name": "Equation",
                        "new_expr": "(x + 1) ^ 2 + 1",
                        "str": "rewriting at 0.1"
                    },
                    "type": "CalculationStep"
                },
                {
                    "latex_res": "\\int_{-1}^{1} (u + 1) (u ^ {2} + 1) ^ {-1} \\,du",
                    "res": "INT u:[-1,1]. (u + 1) * (u ^ 2 + 1) ^ -1",
                    "rule": {
                        "latex_str": "substitute \\(u\\) for \\(x + 1\\)",
                        "name": "Substitution",
                        "str": "substitute u for x + 1",
                        "var_name": "u",
                        "var_subst": "x + 1"
                    },
                    "type": "CalculationStep"
                },
                {
                    "latex_res": "\\int_{-1}^{1} u (u ^ {2} + 1) ^ {-1} + (u ^ {2} + 1) ^ {-1} \\,du",
                    "res": "INT u:[-1,1]. u * (u ^ 2 + 1) ^ -1 + (u ^ 2 + 1) ^ -1",
                    "rule": {
                        "name": "ExpandPolynomial",
                        "str": "expand polynomial"
                    },
                    "type": "CalculationStep"
                },
                {
                    "latex_res": "(\\int_{-1}^{1} u (u ^ {2} + 1) ^ {-1} \\,du) + \\frac{1}{2} \\pi",
                    "res": "(INT u:[-1,1]. u * (u ^ 2 + 1) ^ -1) + 1/2 * pi",
                    "rule": {
                        "name": "FullSimplify",
                        "str": "full simplify"
                    },
                    "type": "CalculationStep"
                },
                {
                    "latex_res": "(\\int_{-1}^{0} u (u ^ {2} + 1) ^ {-1} \\,du) + (\\int_{0}^{1} u (u ^ {2} + 1) ^ {-1} \\,du) + \\frac{1}{2} \\pi",
                    "res": "(INT u:[-1,0]. u * (u ^ 2 + 1) ^ -1) + (INT u:[0,1]. u * (u ^ 2 + 1) ^ -1) + 1/2 * pi",
                    "rule": {
                        "c": "0",
                        "name": "SplitRegion",
                        "str": "split region at 0"
                    },
                    "type": "CalculationStep"
                },
                {
                    "latex_res": "(\\int_{1}^{2} -\\frac{1}{2} v ^ {-1} \\,dv) + (\\int_{0}^{1} u (u ^ {2} + 1) ^ {-1} \\,du) + \\frac{1}{2} \\pi",
                    "res": "(INT v:[1,2]. -1/2 * v ^ -1) + (INT u:[0,1]. u * (u ^ 2 + 1) ^ -1) + 1/2 * pi",
                    "rule": {
                        "latex_str": "substitute \\(v\\) for \\(u ^ {2} + 1\\)",
                        "name": "Substitution",
                        "str": "substitute v for u ^ 2 + 1",
                        "var_name": "v",
                        "var_subst": "u ^ 2 + 1"
                    },
                    "type": "CalculationStep"
                },
                {
                    "latex_res": "(\\int_{0}^{1} u (u ^ {2} + 1) ^ {-1} \\,du) + (-\\frac{1}{2} \\log{(2)} + \\frac{1}{2} \\pi)",
                    "res": "(INT u:[0,1]. u * (u ^ 2 + 1) ^ -1) + (-1/2 * log(2) + 1/2 * pi)",
                    "rule": {
                        "name": "FullSimplify",
                        "str": "full simplify"
                    },
                    "type": "CalculationStep"
                },
                {
                    "latex_res": "(\\int_{1}^{2} \\frac{1}{2} v ^ {-1} \\,dv) + (-\\frac{1}{2} \\log{(2)} + \\frac{1}{2} \\pi)",
                    "res": "(INT v:[1,2]. 1/2 * v ^ -1) + (-1/2 * log(2) + 1/2 * pi)",
                    "rule": {
                        "latex_str": "substitute \\(v\\) for \\(u ^ {2} + 1\\)",
                        "name": "Substitution",
                        "str": "substitute v for u ^ 2 + 1",
                        "var_name": "v",
                        "var_subst": "u ^ 2 + 1"
                    },
                    "type": "CalculationStep"
                },
                {
                    "latex_res": "\\frac{1}{2} \\pi",
                    "res": "1/2 * pi",
                    "rule": {
                        "name": "FullSimplify",
                        "str": "full simplify"
                    },
                    "type": "CalculationStep"
                }
            ],
            "type": "Calculation"
        },
        {
            "latex_start": "\\int_{-\\pi/2}^{\\pi/2} \\cos^{4}(x) \\,dx",
            "start": "INT x:[-pi / 2,pi / 2]. cos(x) ^ 4",
            "steps": [
                {
                    "latex_res": "\\int_{-\\pi/2}^{\\pi/2} (\\cos^{2}(x)) ^ {2} \\,dx",
                    "res": "INT x:[-pi / 2,pi / 2]. cos(x) ^ 2 ^ 2",
                    "rule": {
                        "loc": "0",
                        "name": "Equation",
                        "new_expr": "cos(x) ^ 2 ^ 2",
                        "str": "rewriting at 0"
                    },
                    "type": "CalculationStep"
                },
                {
                    "latex_res": "\\int_{-\\pi/2}^{\\pi/2} (\\frac{\\cos{(2 x)}}{2} + \\frac{1}{2}) ^ {2} \\,dx",
                    "res": "INT x:[-pi / 2,pi / 2]. (cos(2 * x) / 2 + 1/2) ^ 2",
                    "rule": {
                        "loc": "0.0",
                        "name": "RewriteTrigonometric",
                        "rule_name": "TR7",
                        "str": "rewrite trigonometric at 0.0"
                    },
                    "type": "CalculationStep"
                },
                {
                    "latex_res": "\\int_{-\\pi/2}^{\\pi/2} \\frac{1}{4} \\cos^{2}(2 x) + \\frac{1}{2} \\cos{(2 x)} + \\frac{1}{4} \\,dx",
                    "res": "INT x:[-pi / 2,pi / 2]. 1/4 * cos(2 * x) ^ 2 + 1/2 * cos(2 * x) + 1/4",
                    "rule": {
                        "name": "ExpandPolynomial",
                        "str": "expand polynomial"
                    },
                    "type": "CalculationStep"
                },
                {
                    "latex_res": "\\int_{-\\pi}^{\\pi} \\frac{1}{8} \\cos^{2}(u) + \\frac{1}{4} \\cos{(u)} + \\frac{1}{8} \\,du",
                    "res": "INT u:[-pi,pi]. 1/8 * cos(u) ^ 2 + 1/4 * cos(u) + 1/8",
                    "rule": {
                        "latex_str": "substitute \\(u\\) for \\(2 x\\)",
                        "name": "Substitution",
                        "str": "substitute u for 2 * x",
                        "var_name": "u",
                        "var_subst": "2 * x"
                    },
                    "type": "CalculationStep"
                },
                {
                    "latex_res": "\\frac{1}{4} (\\int_{0}^{\\pi} \\cos^{2}(u) \\,du) + \\frac{1}{4} \\pi",
                    "res": "1/4 * (INT u:[0,pi]. cos(u) ^ 2) + 1/4 * pi",
                    "rule": {
                        "name": "FullSimplify",
                        "str": "full simplify"
                    },
                    "type": "CalculationStep"
                },
                {
                    "latex_res": "\\frac{1}{4} (\\int_{0}^{\\pi} \\frac{\\cos{(2 u)}}{2} + \\frac{1}{2} \\,du) + \\frac{1}{4} \\pi",
                    "res": "1/4 * (INT u:[0,pi]. cos(2 * u) / 2 + 1/2) + 1/4 * pi",
                    "rule": {
                        "loc": "0.1.0",
                        "name": "RewriteTrigonometric",
                        "rule_name": "TR7",
                        "str": "rewrite trigonometric at 0.1.0"
                    },
                    "type": "CalculationStep"
                },
                {
                    "latex_res": "\\frac{1}{4} (\\int_{0}^{2 \\pi} \\frac{1}{4} \\cos{(v)} + \\frac{1}{4} \\,dv) + \\frac{1}{4} \\pi",
                    "res": "1/4 * (INT v:[0,2 * pi]. 1/4 * cos(v) + 1/4) + 1/4 * pi",
                    "rule": {
                        "latex_str": "substitute \\(v\\) for \\(2 u\\)",
                        "name": "Substitution",
                        "str": "substitute v for 2 * u",
                        "var_name": "v",
                        "var_subst": "2 * u"
                    },
                    "type": "CalculationStep"
                },
                {
                    "latex_res": "\\frac{3}{8} \\pi",
                    "res": "3/8 * pi",
                    "rule": {
                        "name": "FullSimplify",
                        "str": "full simplify"
                    },
                    "type": "CalculationStep"
                }
            ],
            "type": "Calculation"
        },
        {
            "latex_start": "\\int_{0}^{\\pi} \\sqrt{1 + \\cos{(2 x)}} \\,dx",
            "start": "INT x:[0,pi]. sqrt(1 + cos(2 * x))",
            "steps": [
                {
                    "latex_res": "\\int_{0}^{\\pi} \\sqrt{1 + (-\\sin^{2}(x) + \\cos^{2}(x))} \\,dx",
                    "res": "INT x:[0,pi]. sqrt(1 + (-(sin(x) ^ 2) + cos(x) ^ 2))",
                    "rule": {
                        "latex_str": "rewrite trigonometric on \\(\\cos{(2 x)}\\)",
                        "name": "RewriteTrigonometric",
                        "rewrite_term": "cos(2 * x)",
                        "rule_name": "TR11",
                        "str": "rewrite trigonometric on cos(2 * x)"
                    },
                    "type": "CalculationStep"
                },
                {
                    "latex_res": "\\int_{0}^{\\pi} \\sqrt{1 + (\\cos^{2}(x) - 1 + \\cos^{2}(x))} \\,dx",
                    "res": "INT x:[0,pi]. sqrt(1 + (cos(x) ^ 2 - 1 + cos(x) ^ 2))",
                    "rule": {
                        "latex_str": "rewrite trigonometric on \\(-\\sin^{2}(x)\\)",
                        "name": "RewriteTrigonometric",
                        "rewrite_term": "-(sin(x) ^ 2)",
                        "rule_name": "TR5",
                        "str": "rewrite trigonometric on -(sin(x) ^ 2)"
                    },
                    "type": "CalculationStep"
                },
                {
                    "latex_res": "\\sqrt{2} (\\int_{0}^{\\pi} \\left| \\cos{(x)} \\right| \\,dx)",
                    "res": "sqrt(2) * (INT x:[0,pi]. abs(cos(x)))",
                    "rule": {
                        "name": "FullSimplify",
                        "str": "full simplify"
                    },
                    "type": "CalculationStep"
                },
                {
                    "latex_res": "\\sqrt{2} ((\\int_{0}^{\\pi/2} \\cos{(x)} \\,dx) + (\\int_{\\pi/2}^{\\pi} -\\cos{(x)} \\,dx))",
                    "res": "sqrt(2) * ((INT x:[0,pi / 2]. cos(x)) + (INT x:[pi / 2,pi]. -cos(x)))",
                    "rule": {
                        "loc": "1",
                        "name": "ElimAbs",
                        "str": "eliminate absolute values at 1"
                    },
                    "type": "CalculationStep"
                },
                {
                    "latex_res": "2 \\sqrt{2}",
                    "res": "2 * sqrt(2)",
                    "rule": {
                        "name": "FullSimplify",
                        "str": "full simplify"
                    },
                    "type": "CalculationStep"
                }
            ],
            "type": "Calculation"
        },
        {
            "latex_start": "\\int_{0}^{1} x e^{-x} \\,dx",
            "start": "INT x:[0,1]. x * exp(-x)",
            "steps": [
                {
                    "latex_res": "(\\left. -x e^{-x} \\right\\vert_{x=0}^{1}) - (\\int_{0}^{1} -e^{-x} \\,dx)",
                    "res": "([-(x * exp(-x))]_x=0,1) - (INT x:[0,1]. -exp(-x))",
                    "rule": {
                        "latex_str": "integrate by parts \\(u \\to x, v \\to -e^{-x}\\)",
                        "name": "IntegrationByParts",
                        "str": "integrate by parts u -> x, v -> -exp(-x)",
                        "u": "x",
                        "v": "-exp(-x)"
                    },
                    "type": "CalculationStep"
                },
                {
                    "latex_res": "(\\int_{0}^{1} e^{-x} \\,dx) - e^{-1}",
                    "res": "(INT x:[0,1]. exp(-x)) - exp(-1)",
                    "rule": {
                        "name": "FullSimplify",
                        "str": "full simplify"
                    },
                    "type": "CalculationStep"
                },
                {
                    "latex_res": "(\\int_{-1}^{0} e^{u} \\,du) - e^{-1}",
                    "res": "(INT u:[-1,0]. exp(u)) - exp(-1)",
                    "rule": {
                        "latex_str": "substitute \\(u\\) for \\(-x\\)",
                        "name": "Substitution",
                        "str": "substitute u for -x",
                        "var_name": "u",
                        "var_subst": "-x"
                    },
                    "type": "CalculationStep"
                },
                {
                    "latex_res": "-2 e^{-1} + 1",
                    "res": "-2 * exp(-1) + 1",
                    "rule": {
                        "name": "FullSimplify",
                        "str": "full simplify"
                    },
                    "type": "CalculationStep"
                }
            ],
            "type": "Calculation"
        },
        {
            "latex_start": "\\int_{1}^{e} x \\log{(x)} \\,dx",
            "start": "INT x:[1,exp(1)]. x * log(x)",
            "steps": [
                {
                    "latex_res": "(\\left. \\frac{1}{2} x ^ {2} \\log{(x)} \\right\\vert_{x=1}^{e}) - (\\int_{1}^{e} \\frac{1}{2} x \\,dx)",
                    "res": "([1/2 * x ^ 2 * log(x)]_x=1,exp(1)) - (INT x:[1,exp(1)]. 1/2 * x)",
                    "rule": {
                        "latex_str": "integrate by parts \\(u \\to \\frac{\\log{(x)}}{2}, v \\to x ^ {2}\\)",
                        "name": "IntegrationByParts",
                        "str": "integrate by parts u -> log(x) / 2, v -> x ^ 2",
                        "u": "log(x) / 2",
                        "v": "x ^ 2"
                    },
                    "type": "CalculationStep"
                },
                {
                    "latex_res": "\\frac{1}{4} e^{2} + \\frac{1}{4}",
                    "res": "1/4 * exp(2) + 1/4",
                    "rule": {
                        "name": "FullSimplify",
                        "str": "full simplify"
                    },
                    "type": "CalculationStep"
                }
            ],
            "type": "Calculation"
        },
        {
            "latex_start": "\\int_{\\pi/4}^{\\pi/3} \\frac{x}{\\sin^{2}(x)} \\,dx",
            "start": "INT x:[pi / 4,pi / 3]. x / sin(x) ^ 2",
            "steps": [
                {
                    "latex_res": "\\int_{\\pi/4}^{\\pi/3} x \\csc^{2}(x) \\,dx",
                    "res": "INT x:[pi / 4,pi / 3]. x * csc(x) ^ 2",
                    "rule": {
                        "loc": "0",
                        "name": "RewriteTrigonometric",
                        "rule_name": "TR111",
                        "str": "rewrite trigonometric at 0"
                    },
                    "type": "CalculationStep"
                },
                {
                    "latex_res": "(\\left. -x \\cot{(x)} \\right\\vert_{x=\\pi/4}^{\\pi/3}) - (\\int_{\\pi/4}^{\\pi/3} -\\cot{(x)} \\,dx)",
                    "res": "([-(x * cot(x))]_x=pi / 4,pi / 3) - (INT x:[pi / 4,pi / 3]. -cot(x))",
                    "rule": {
                        "latex_str": "integrate by parts \\(u \\to x, v \\to -\\cot{(x)}\\)",
                        "name": "IntegrationByParts",
                        "str": "integrate by parts u -> x, v -> -cot(x)",
                        "u": "x",
                        "v": "-cot(x)"
                    },
                    "type": "CalculationStep"
                },
                {
                    "latex_res": "-\\frac{1}{9} \\sqrt{3} \\pi + \\frac{1}{4} \\pi + (\\int_{1/4 \\pi}^{1/3 \\pi} \\cot{(x)} \\,dx)",
                    "res": "-1/9 * sqrt(3) * pi + 1/4 * pi + (INT x:[1/4 * pi,1/3 * pi]. cot(x))",
                    "rule": {
                        "name": "FullSimplify",
                        "str": "full simplify"
                    },
                    "type": "CalculationStep"
                },
                {
                    "latex_res": "-\\frac{1}{9} \\sqrt{3} \\pi + \\frac{1}{4} \\pi + (\\int_{1/4 \\pi}^{1/3 \\pi} \\frac{\\cos{(x)}}{\\sin{(x)}} \\,dx)",
                    "res": "-1/9 * sqrt(3) * pi + 1/4 * pi + (INT x:[1/4 * pi,1/3 * pi]. cos(x) / sin(x))",
                    "rule": {
                        "loc": "1.0",
                        "name": "RewriteTrigonometric",
                        "rule_name": "TR2",
                        "str": "rewrite trigonometric at 1.0"
                    },
                    "type": "CalculationStep"
                },
                {
                    "latex_res": "-\\frac{1}{9} \\sqrt{3} \\pi + \\frac{1}{4} \\pi + (\\int_{1/2 \\sqrt{2}}^{1/2 \\sqrt{3}} u ^ {-1} \\,du)",
                    "res": "-1/9 * sqrt(3) * pi + 1/4 * pi + (INT u:[1/2 * sqrt(2),1/2 * sqrt(3)]. u ^ -1)",
                    "rule": {
                        "latex_str": "substitute \\(u\\) for \\(\\sin{(x)}\\)",
                        "name": "Substitution",
                        "str": "substitute u for sin(x)",
                        "var_name": "u",
                        "var_subst": "sin(x)"
                    },
                    "type": "CalculationStep"
                },
                {
                    "latex_res": "-\\frac{1}{9} \\sqrt{3} \\pi - \\frac{1}{2} \\log{(2)} + \\frac{1}{2} \\log{(3)} + \\frac{1}{4} \\pi",
                    "res": "-1/9 * sqrt(3) * pi - 1/2 * log(2) + 1/2 * log(3) + 1/4 * pi",
                    "rule": {
                        "name": "FullSimplify",
                        "str": "full simplify"
                    },
                    "type": "CalculationStep"
                }
            ],
            "type": "Calculation"
        },
        {
            "latex_start": "\\int_{1}^{4} x ^ {-1/2} \\log{(x)} \\,dx",
            "start": "INT x:[1,4]. x ^ (-1/2) * log(x)",
            "steps": [
                {
                    "latex_res": "(\\left. 2 \\sqrt{x} \\log{(x)} \\right\\vert_{x=1}^{4}) - (\\int_{1}^{4} 2 x ^ {-1/2} \\,dx)",
                    "res": "([2 * sqrt(x) * log(x)]_x=1,4) - (INT x:[1,4]. 2 * x ^ (-1/2))",
                    "rule": {
                        "latex_str": "integrate by parts \\(u \\to 2 \\log{(x)}, v \\to \\sqrt{x}\\)",
                        "name": "IntegrationByParts",
                        "str": "integrate by parts u -> 2 * log(x), v -> sqrt(x)",
                        "u": "2 * log(x)",
                        "v": "sqrt(x)"
                    },
                    "type": "CalculationStep"
                },
                {
                    "latex_res": "8 \\log{(2)} - 4",
                    "res": "8 * log(2) - 4",
                    "rule": {
                        "name": "FullSimplify",
                        "str": "full simplify"
                    },
                    "type": "CalculationStep"
                }
            ],
            "type": "Calculation"
        },
        {
            "latex_start": "\\int_{0}^{1} x \\arctan{(x)} \\,dx",
            "start": "INT x:[0,1]. x * atan(x)",
            "steps": [
                {
                    "latex_res": "(\\left. \\frac{1}{2} x ^ {2} \\arctan{(x)} \\right\\vert_{x=0}^{1}) - (\\int_{0}^{1} \\frac{1}{2} x ^ {2} (x ^ {2} + 1) ^ {-1} \\,dx)",
                    "res": "([1/2 * x ^ 2 * atan(x)]_x=0,1) - (INT x:[0,1]. 1/2 * x ^ 2 * (x ^ 2 + 1) ^ -1)",
                    "rule": {
                        "latex_str": "integrate by parts \\(u \\to \\frac{\\arctan{(x)}}{2}, v \\to x ^ {2}\\)",
                        "name": "IntegrationByParts",
                        "str": "integrate by parts u -> atan(x) / 2, v -> x ^ 2",
                        "u": "atan(x) / 2",
                        "v": "x ^ 2"
                    },
                    "type": "CalculationStep"
                },
                {
                    "latex_res": "-\\frac{1}{2} (\\int_{0}^{1} x ^ {2} (x ^ {2} + 1) ^ {-1} \\,dx) + \\frac{1}{8} \\pi",
                    "res": "-1/2 * (INT x:[0,1]. x ^ 2 * (x ^ 2 + 1) ^ -1) + 1/8 * pi",
                    "rule": {
                        "name": "FullSimplify",
                        "str": "full simplify"
                    },
                    "type": "CalculationStep"
                },
                {
                    "latex_res": "-\\frac{1}{2} (\\int_{0}^{1} 1 - \\frac{1}{x ^ {2} + 1} \\,dx) + \\frac{1}{8} \\pi",
                    "res": "-1/2 * (INT x:[0,1]. 1 - 1 / (x ^ 2 + 1)) + 1/8 * pi",
                    "rule": {
                        "loc": "0.1",
                        "name": "PolynomialDivision",
                        "str": "polynomial division at 0.1"
                    },
                    "type": "CalculationStep"
                },
                {
                    "latex_res": "\\frac{1}{4} \\pi - \\frac{1}{2}",
                    "res": "1/4 * pi - 1/2",
                    "rule": {
                        "name": "FullSimplify",
                        "str": "full simplify"
                    },
                    "type": "CalculationStep"
                }
            ],
            "type": "Calculation"
        },
        {
            "latex_start": "\\int_{0}^{\\pi/2} \\cos{(x)} e^{2 x} \\,dx",
            "start": "INT x:[0,pi / 2]. cos(x) * exp(2 * x)",
            "steps": [
                {
                    "latex_res": "(\\left. e^{2 x} \\sin{(x)} \\right\\vert_{x=0}^{\\pi/2}) - (\\int_{0}^{\\pi/2} 2 e^{2 x} \\sin{(x)} \\,dx)",
                    "res": "([exp(2 * x) * sin(x)]_x=0,pi / 2) - (INT x:[0,pi / 2]. 2 * exp(2 * x) * sin(x))",
                    "rule": {
                        "latex_str": "integrate by parts \\(u \\to e^{2 x}, v \\to \\sin{(x)}\\)",
                        "name": "IntegrationByParts",
                        "str": "integrate by parts u -> exp(2 * x), v -> sin(x)",
                        "u": "exp(2 * x)",
                        "v": "sin(x)"
                    },
                    "type": "CalculationStep"
                },
                {
                    "latex_res": "-2 (\\int_{0}^{1/2 \\pi} e^{2 x} \\sin{(x)} \\,dx) + e^{\\pi}",
                    "res": "-2 * (INT x:[0,1/2 * pi]. exp(2 * x) * sin(x)) + exp(pi)",
                    "rule": {
                        "name": "FullSimplify",
                        "str": "full simplify"
                    },
                    "type": "CalculationStep"
                },
                {
                    "latex_res": "-2 ((\\left. -\\cos{(x)} e^{2 x} \\right\\vert_{x=0}^{1/2 \\pi}) - (\\int_{0}^{1/2 \\pi} -2 \\cos{(x)} e^{2 x} \\,dx)) + e^{\\pi}",
                    "res": "-2 * (([-(cos(x) * exp(2 * x))]_x=0,1/2 * pi) - (INT x:[0,1/2 * pi]. -2 * cos(x) * exp(2 * x))) + exp(pi)",
                    "rule": {
                        "latex_str": "integrate by parts \\(u \\to e^{2 x}, v \\to -\\cos{(x)}\\)",
                        "name": "IntegrationByParts",
                        "str": "integrate by parts u -> exp(2 * x), v -> -cos(x)",
                        "u": "exp(2 * x)",
                        "v": "-cos(x)"
                    },
                    "type": "CalculationStep"
                },
                {
                    "latex_res": "-4 (\\int_{0}^{1/2 \\pi} \\cos{(x)} e^{2 x} \\,dx) + (e^{\\pi} - 2)",
                    "res": "-4 * (INT x:[0,1/2 * pi]. cos(x) * exp(2 * x)) + (exp(pi) - 2)",
                    "rule": {
                        "name": "FullSimplify",
                        "str": "full simplify"
                    },
                    "type": "CalculationStep"
                },
                {
                    "latex_res": "\\frac{1}{5} e^{\\pi} - \\frac{2}{5}",
                    "res": "1/5 * exp(pi) - 2/5",
                    "rule": {
                        "lhs": "INT x:[0,1/2 * pi]. cos(x) * exp(2 * x)",
                        "name": "IntegrateByEquation",
                        "str": "integrate by equation"
                    },
                    "type": "CalculationStep"
                }
            ],
            "type": "Calculation"
        },
        {
            "latex_start": "\\int_{0}^{\\pi} (x \\sin{(x)}) ^ {2} \\,dx",
            "start": "INT x:[0,pi]. (x * sin(x)) ^ 2",
            "steps": [
                {
                    "latex_res": "\\int_{0}^{\\pi} x ^ {2} \\sin^{2}(x) \\,dx",
                    "res": "INT x:[0,pi]. x ^ 2 * sin(x) ^ 2",
                    "rule": {
                        "name": "FullSimplify",
                        "str": "full simplify"
                    },
                    "type": "CalculationStep"
                },
                {
                    "latex_res": "\\int_{0}^{\\pi} x ^ {2} (\\frac{1}{2} - \\frac{\\cos{(2 x)}}{2}) \\,dx",
                    "res": "INT x:[0,pi]. x ^ 2 * (1/2 - cos(2 * x) / 2)",
                    "rule": {
                        "loc": "0.1",
                        "name": "RewriteTrigonometric",
                        "rule_name": "TR8",
                        "str": "rewrite trigonometric at 0.1"
                    },
                    "type": "CalculationStep"
                },
                {
                    "latex_res": "\\int_{0}^{\\pi} -\\frac{1}{2} x ^ {2} \\cos{(2 x)} + \\frac{1}{2} x ^ {2} \\,dx",
                    "res": "INT x:[0,pi]. -1/2 * x ^ 2 * cos(2 * x) + 1/2 * x ^ 2",
                    "rule": {
                        "name": "ExpandPolynomial",
                        "str": "expand polynomial"
                    },
                    "type": "CalculationStep"
                },
                {
                    "latex_res": "-\\frac{1}{2} (\\int_{0}^{\\pi} x ^ {2} \\cos{(2 x)} \\,dx) + \\frac{1}{6} \\pi ^ {3}",
                    "res": "-1/2 * (INT x:[0,pi]. x ^ 2 * cos(2 * x)) + 1/6 * pi ^ 3",
                    "rule": {
                        "name": "FullSimplify",
                        "str": "full simplify"
                    },
                    "type": "CalculationStep"
                },
                {
                    "latex_res": "-\\frac{1}{2} ((\\left. \\frac{1}{2} x ^ {2} \\sin{(2 x)} \\right\\vert_{x=0}^{\\pi}) - (\\int_{0}^{\\pi} x \\sin{(2 x)} \\,dx)) + \\frac{1}{6} \\pi ^ {3}",
                    "res": "-1/2 * (([1/2 * x ^ 2 * sin(2 * x)]_x=0,pi) - (INT x:[0,pi]. x * sin(2 * x))) + 1/6 * pi ^ 3",
                    "rule": {
                        "latex_str": "integrate by parts \\(u \\to \\frac{x ^ {2}}{2}, v \\to \\sin{(2 x)}\\)",
                        "name": "IntegrationByParts",
                        "str": "integrate by parts u -> x ^ 2 / 2, v -> sin(2 * x)",
                        "u": "x ^ 2 / 2",
                        "v": "sin(2 * x)"
                    },
                    "type": "CalculationStep"
                },
                {
                    "latex_res": "\\frac{1}{2} (\\int_{0}^{\\pi} x \\sin{(2 x)} \\,dx) + \\frac{1}{6} \\pi ^ {3}",
                    "res": "1/2 * (INT x:[0,pi]. x * sin(2 * x)) + 1/6 * pi ^ 3",
                    "rule": {
                        "name": "FullSimplify",
                        "str": "full simplify"
                    },
                    "type": "CalculationStep"
                },
                {
                    "latex_res": "\\frac{1}{2} ((\\left. -\\frac{1}{2} x \\cos{(2 x)} \\right\\vert_{x=0}^{\\pi}) - (\\int_{0}^{\\pi} -\\frac{1}{2} \\cos{(2 x)} \\,dx)) + \\frac{1}{6} \\pi ^ {3}",
                    "res": "1/2 * (([-1/2 * x * cos(2 * x)]_x=0,pi) - (INT x:[0,pi]. -1/2 * cos(2 * x))) + 1/6 * pi ^ 3",
                    "rule": {
                        "latex_str": "integrate by parts \\(u \\to \\frac{x}{2}, v \\to -\\cos{(2 x)}\\)",
                        "name": "IntegrationByParts",
                        "str": "integrate by parts u -> x / 2, v -> -cos(2 * x)",
                        "u": "x / 2",
                        "v": "-cos(2 * x)"
                    },
                    "type": "CalculationStep"
                },
                {
                    "latex_res": "\\frac{1}{6} \\pi ^ {3} - \\frac{1}{4} \\pi + \\frac{1}{4} (\\int_{0}^{\\pi} \\cos{(2 x)} \\,dx)",
                    "res": "1/6 * pi ^ 3 - 1/4 * pi + 1/4 * (INT x:[0,pi]. cos(2 * x))",
                    "rule": {
                        "name": "FullSimplify",
                        "str": "full simplify"
                    },
                    "type": "CalculationStep"
                },
                {
                    "latex_res": "\\frac{1}{6} \\pi ^ {3} - \\frac{1}{4} \\pi + \\frac{1}{4} (\\int_{0}^{2 \\pi} \\frac{1}{2} \\cos{(u)} \\,du)",
                    "res": "1/6 * pi ^ 3 - 1/4 * pi + 1/4 * (INT u:[0,2 * pi]. 1/2 * cos(u))",
                    "rule": {
                        "latex_str": "substitute \\(u\\) for \\(2 x\\)",
                        "name": "Substitution",
                        "str": "substitute u for 2 * x",
                        "var_name": "u",
                        "var_subst": "2 * x"
                    },
                    "type": "CalculationStep"
                },
                {
                    "latex_res": "\\frac{1}{6} \\pi ^ {3} - \\frac{1}{4} \\pi",
                    "res": "1/6 * pi ^ 3 - 1/4 * pi",
                    "rule": {
                        "name": "FullSimplify",
                        "str": "full simplify"
                    },
                    "type": "CalculationStep"
                }
            ],
            "type": "Calculation"
        },
        {
            "latex_start": "\\int_{1}^{e} \\sin{(\\log{(x)})} \\,dx",
            "start": "INT x:[1,exp(1)]. sin(log(x))",
            "steps": [
                {
                    "latex_res": "\\int_{0}^{1} e^{u} \\sin{(u)} \\,du",
                    "res": "INT u:[0,1]. exp(u) * sin(u)",
                    "rule": {
                        "latex_str": "substitute \\(u\\) for \\(\\log{(x)}\\)",
                        "name": "Substitution",
                        "str": "substitute u for log(x)",
                        "var_name": "u",
                        "var_subst": "log(x)"
                    },
                    "type": "CalculationStep"
                },
                {
                    "latex_res": "(\\left. -\\cos{(u)} e^{u} \\right\\vert_{u=0}^{1}) - (\\int_{0}^{1} -\\cos{(u)} e^{u} \\,du)",
                    "res": "([-(cos(u) * exp(u))]_u=0,1) - (INT u:[0,1]. -(cos(u) * exp(u)))",
                    "rule": {
                        "latex_str": "integrate by parts \\(u \\to -e^{u}, v \\to \\cos{(u)}\\)",
                        "name": "IntegrationByParts",
                        "str": "integrate by parts u -> -exp(u), v -> cos(u)",
                        "u": "-exp(u)",
                        "v": "cos(u)"
                    },
                    "type": "CalculationStep"
                },
                {
                    "latex_res": "-\\cos{(1)} e + 1 + (\\int_{0}^{1} \\cos{(u)} e^{u} \\,du)",
                    "res": "-(cos(1) * exp(1)) + 1 + (INT u:[0,1]. cos(u) * exp(u))",
                    "rule": {
                        "name": "FullSimplify",
                        "str": "full simplify"
                    },
                    "type": "CalculationStep"
                },
                {
                    "latex_res": "-\\cos{(1)} e + 1 + ((\\left. e^{u} \\sin{(u)} \\right\\vert_{u=0}^{1}) - (\\int_{0}^{1} e^{u} \\sin{(u)} \\,du))",
                    "res": "-(cos(1) * exp(1)) + 1 + (([exp(u) * sin(u)]_u=0,1) - (INT u:[0,1]. exp(u) * sin(u)))",
                    "rule": {
                        "latex_str": "integrate by parts \\(u \\to e^{u}, v \\to \\sin{(u)}\\)",
                        "name": "IntegrationByParts",
                        "str": "integrate by parts u -> exp(u), v -> sin(u)",
                        "u": "exp(u)",
                        "v": "sin(u)"
                    },
                    "type": "CalculationStep"
                },
                {
                    "latex_res": "-\\cos{(1)} e + e \\sin{(1)} + 1 - (\\int_{0}^{1} e^{u} \\sin{(u)} \\,du)",
                    "res": "-(cos(1) * exp(1)) + exp(1) * sin(1) + 1 - (INT u:[0,1]. exp(u) * sin(u))",
                    "rule": {
                        "name": "FullSimplify",
                        "str": "full simplify"
                    },
                    "type": "CalculationStep"
                },
                {
                    "latex_res": "-\\frac{1}{2} \\cos{(1)} e + \\frac{1}{2} e \\sin{(1)} + \\frac{1}{2}",
                    "res": "-1/2 * cos(1) * exp(1) + 1/2 * exp(1) * sin(1) + 1/2",
                    "rule": {
                        "lhs": "INT u:[0,1]. exp(u) * sin(u)",
                        "name": "IntegrateByEquation",
                        "str": "integrate by equation"
                    },
                    "type": "CalculationStep"
                }
            ],
            "type": "Calculation"
        },
        {
            "latex_start": "\\int_{1/e}^{e} \\left| \\log{(x)} \\right| \\,dx",
            "start": "INT x:[1 / exp(1),exp(1)]. abs(log(x))",
            "steps": [
                {
                    "latex_res": "(\\int_{1}^{e} \\log{(x)} \\,dx) + (\\int_{e^{-1}}^{1} -\\log{(x)} \\,dx)",
                    "res": "(INT x:[1,exp(1)]. log(x)) + (INT x:[exp(-1),1]. -log(x))",
                    "rule": {
                        "name": "ElimAbs",
                        "str": "eliminate absolute values"
                    },
                    "type": "CalculationStep"
                },
                {
                    "latex_res": "(\\left. x \\log{(x)} \\right\\vert_{x=1}^{e}) - (\\int_{1}^{e} 1 \\,dx) + (\\int_{e^{-1}}^{1} -\\log{(x)} \\,dx)",
                    "res": "([x * log(x)]_x=1,exp(1)) - (INT x:[1,exp(1)]. 1) + (INT x:[exp(-1),1]. -log(x))",
                    "rule": {
                        "latex_str": "integrate by parts \\(u \\to \\log{(x)}, v \\to x\\)",
                        "name": "IntegrationByParts",
                        "str": "integrate by parts u -> log(x), v -> x",
                        "u": "log(x)",
                        "v": "x"
                    },
                    "type": "CalculationStep"
                },
                {
                    "latex_res": "-(\\int_{e^{-1}}^{1} \\log{(x)} \\,dx) + 1",
                    "res": "-(INT x:[exp(-1),1]. log(x)) + 1",
                    "rule": {
                        "name": "FullSimplify",
                        "str": "full simplify"
                    },
                    "type": "CalculationStep"
                },
                {
                    "latex_res": "-((\\left. x \\log{(x)} \\right\\vert_{x=e^{-1}}^{1}) - (\\int_{e^{-1}}^{1} 1 \\,dx)) + 1",
                    "res": "-(([x * log(x)]_x=exp(-1),1) - (INT x:[exp(-1),1]. 1)) + 1",
                    "rule": {
                        "latex_str": "integrate by parts \\(u \\to \\log{(x)}, v \\to x\\)",
                        "name": "IntegrationByParts",
                        "str": "integrate by parts u -> log(x), v -> x",
                        "u": "log(x)",
                        "v": "x"
                    },
                    "type": "CalculationStep"
                },
                {
                    "latex_res": "-2 e^{-1} + 2",
                    "res": "-2 * exp(-1) + 2",
                    "rule": {
                        "name": "FullSimplify",
                        "str": "full simplify"
                    },
                    "type": "CalculationStep"
                }
            ],
            "type": "Calculation"
        }
    ],
    "name": "Tongji"
}